setup.py
Slack_Zendesk_Integration_webhook/__init__.py
Slack_Zendesk_integration_webhook.egg-info/PKG-INFO
Slack_Zendesk_integration_webhook.egg-info/SOURCES.txt
Slack_Zendesk_integration_webhook.egg-info/dependency_links.txt
Slack_Zendesk_integration_webhook.egg-info/not-zip-safe
Slack_Zendesk_integration_webhook.egg-info/top_level.txt