Metadata-Version: 1.0
Name: Slack-Zendesk-integration-webhook
Version: 0.1
Summary: Slack Integration Webhook
Home-page: http://github.com/storborg/funniest
Author: Kelvin@prism.com
Author-email: https://github.com/Kelvin-prismskylabs/Slack-Zendesk-Integration.git
License: NA
Platform: UNKNOWN
